<annotation>
  <filename>NG-249.jpg</filename>
  <folder>Documents</folder>
  <object>
    <bndbox>
      <xmax>933</xmax>
      <xmin>885</xmin>
      <ymax>184</ymax>
      <ymin>119</ymin>
    </bndbox>
    <difficult>0</difficult>
    <name>Black Spot</name>
    <pose>Unspecified</pose>
    <truncated>0</truncated>
  </object>
  <object>
    <bndbox>
      <xmax>630</xmax>
      <xmin>591</xmin>
      <ymax>188</ymax>
      <ymin>127</ymin>
    </bndbox>
    <difficult>0</difficult>
    <name>Snowflake Spot</name>
    <pose>Unspecified</pose>
    <truncated>0</truncated>
  </object>
  <object>
    <bndbox>
      <xmax>431</xmax>
      <xmin>398</xmin>
      <ymax>578</ymax>
      <ymin>513</ymin>
    </bndbox>
    <difficult>0</difficult>
    <name>Snowflake Spot</name>
    <pose>Unspecified</pose>
    <truncated>0</truncated>
  </object>
  <object>
    <bndbox>
      <xmax>1297</xmax>
      <xmin>1263</xmin>
      <ymax>458</ymax>
      <ymin>424</ymin>
    </bndbox>
    <difficult>0</difficult>
    <name>Snowflake Spot</name>
    <pose>Unspecified</pose>
    <truncated>0</truncated>
  </object>
  <object>
    <bndbox>
      <xmax>1266</xmax>
      <xmin>1248</xmin>
      <ymax>884</ymax>
      <ymin>857</ymin>
    </bndbox>
    <difficult>0</difficult>
    <name>Snowflake Spot</name>
    <pose>Unspecified</pose>
    <truncated>0</truncated>
  </object>
  <object>
    <bndbox>
      <xmax>1664</xmax>
      <xmin>1637</xmin>
      <ymax>666</ymax>
      <ymin>639</ymin>
    </bndbox>
    <difficult>0</difficult>
    <name>Snowflake Spot</name>
    <pose>Unspecified</pose>
    <truncated>0</truncated>
  </object>
  <object>
    <bndbox>
      <xmax>1075</xmax>
      <xmin>1049</xmin>
      <ymax>429</ymax>
      <ymin>386</ymin>
    </bndbox>
    <difficult>0</difficult>
    <name>Snowflake Spot</name>
    <pose>Unspecified</pose>
    <truncated>0</truncated>
  </object>
  <object>
    <bndbox>
      <xmax>1670</xmax>
      <xmin>1646</xmin>
      <ymax>120</ymax>
      <ymin>88</ymin>
    </bndbox>
    <difficult>0</difficult>
    <name>Snowflake Spot</name>
    <pose>Unspecified</pose>
    <truncated>0</truncated>
  </object>
  <object>
    <bndbox>
      <xmax>1453</xmax>
      <xmin>1407</xmin>
      <ymax>348</ymax>
      <ymin>303</ymin>
    </bndbox>
    <difficult>0</difficult>
    <name>Black Spot</name>
    <pose>Unspecified</pose>
    <truncated>0</truncated>
  </object>
  <object>
    <bndbox>
      <xmax>1100</xmax>
      <xmin>1072</xmin>
      <ymax>716</ymax>
      <ymin>670</ymin>
    </bndbox>
    <difficult>0</difficult>
    <name>Black Spot</name>
    <pose>Unspecified</pose>
    <truncated>0</truncated>
  </object>
  <object>
    <bndbox>
      <xmax>1739</xmax>
      <xmin>1700</xmin>
      <ymax>905</ymax>
      <ymin>846</ymin>
    </bndbox>
    <difficult>0</difficult>
    <name>Black Spot</name>
    <pose>Unspecified</pose>
    <truncated>0</truncated>
  </object>
  <object>
    <bndbox>
      <xmax>635</xmax>
      <xmin>598</xmin>
      <ymax>925</ymax>
      <ymin>786</ymin>
    </bndbox>
    <difficult>0</difficult>
    <name>Gate Rupture</name>
    <pose>Unspecified</pose>
    <truncated>0</truncated>
  </object>
  <object>
    <bndbox>
      <xmax>263</xmax>
      <xmin>225</xmin>
      <ymax>642</ymax>
      <ymin>500</ymin>
    </bndbox>
    <difficult>0</difficult>
    <name>Gate Rupture</name>
    <pose>Unspecified</pose>
    <truncated>0</truncated>
  </object>
  <object>
    <bndbox>
      <xmax>631</xmax>
      <xmin>593</xmin>
      <ymax>350</ymax>
      <ymin>206</ymin>
    </bndbox>
    <difficult>0</difficult>
    <name>Gate Rupture</name>
    <pose>Unspecified</pose>
    <truncated>0</truncated>
  </object>
  <object>
    <bndbox>
      <xmax>1808</xmax>
      <xmin>1781</xmin>
      <ymax>205</ymax>
      <ymin>58</ymin>
    </bndbox>
    <difficult>0</difficult>
    <name>Gate Rupture</name>
    <pose>Unspecified</pose>
    <truncated>0</truncated>
  </object>
  <object>
    <bndbox>
      <xmax>1213</xmax>
      <xmin>1188</xmin>
      <ymax>494</ymax>
      <ymin>347</ymin>
    </bndbox>
    <difficult>0</difficult>
    <name>Gate Rupture</name>
    <pose>Unspecified</pose>
    <truncated>0</truncated>
  </object>
  <object>
    <bndbox>
      <xmax>926</xmax>
      <xmin>885</xmin>
      <ymax>642</ymax>
      <ymin>495</ymin>
    </bndbox>
    <difficult>0</difficult>
    <name>Gate Rupture</name>
    <pose>Unspecified</pose>
    <truncated>0</truncated>
  </object>
  <object>
    <bndbox>
      <xmax>1085</xmax>
      <xmin>1055</xmin>
      <ymax>636</ymax>
      <ymin>494</ymin>
    </bndbox>
    <difficult>0</difficult>
    <name>Gate Rupture</name>
    <pose>Unspecified</pose>
    <truncated>0</truncated>
  </object>
  <object>
    <bndbox>
      <xmax>1011</xmax>
      <xmin>981</xmin>
      <ymax>640</ymax>
      <ymin>496</ymin>
    </bndbox>
    <difficult>0</difficult>
    <name>Gate Rupture</name>
    <pose>Unspecified</pose>
    <truncated>0</truncated>
  </object>
  <object>
    <bndbox>
      <xmax>841</xmax>
      <xmin>813</xmin>
      <ymax>640</ymax>
      <ymin>498</ymin>
    </bndbox>
    <difficult>0</difficult>
    <name>Gate Rupture</name>
    <pose>Unspecified</pose>
    <truncated>0</truncated>
  </object>
  <object>
    <bndbox>
      <xmax>483</xmax>
      <xmin>447</xmin>
      <ymax>929</ymax>
      <ymin>786</ymin>
    </bndbox>
    <difficult>0</difficult>
    <name>Gate Rupture</name>
    <pose>Unspecified</pose>
    <truncated>0</truncated>
  </object>
  <object>
    <bndbox>
      <xmax>411</xmax>
      <xmin>377</xmin>
      <ymax>931</ymax>
      <ymin>791</ymin>
    </bndbox>
    <difficult>0</difficult>
    <name>Gate Rupture</name>
    <pose>Unspecified</pose>
    <truncated>0</truncated>
  </object>
  <object>
    <bndbox>
      <xmax>566</xmax>
      <xmin>535</xmin>
      <ymax>500</ymax>
      <ymin>356</ymin>
    </bndbox>
    <difficult>0</difficult>
    <name>Gate Rupture</name>
    <pose>Unspecified</pose>
    <truncated>0</truncated>
  </object>
  <object>
    <bndbox>
      <xmax>859</xmax>
      <xmin>828</xmin>
      <ymax>497</ymax>
      <ymin>352</ymin>
    </bndbox>
    <difficult>0</difficult>
    <name>Gate Rupture</name>
    <pose>Unspecified</pose>
    <truncated>0</truncated>
  </object>
  <object>
    <bndbox>
      <xmax>268</xmax>
      <xmin>236</xmin>
      <ymax>497</ymax>
      <ymin>356</ymin>
    </bndbox>
    <difficult>0</difficult>
    <name>Gate Rupture</name>
    <pose>Unspecified</pose>
    <truncated>0</truncated>
  </object>
  <object>
    <bndbox>
      <xmax>183</xmax>
      <xmin>146</xmin>
      <ymax>641</ymax>
      <ymin>496</ymin>
    </bndbox>
    <difficult>0</difficult>
    <name>Gate Rupture</name>
    <pose>Unspecified</pose>
    <truncated>0</truncated>
  </object>
  <object>
    <bndbox>
      <xmax>108</xmax>
      <xmin>75</xmin>
      <ymax>644</ymax>
      <ymin>497</ymin>
    </bndbox>
    <difficult>0</difficult>
    <name>Gate Rupture</name>
    <pose>Unspecified</pose>
    <truncated>0</truncated>
  </object>
  <object>
    <bndbox>
      <xmax>1371</xmax>
      <xmin>1336</xmin>
      <ymax>494</ymax>
      <ymin>353</ymin>
    </bndbox>
    <difficult>0</difficult>
    <name>Gate Rupture</name>
    <pose>Unspecified</pose>
    <truncated>0</truncated>
  </object>
  <object>
    <bndbox>
      <xmax>1303</xmax>
      <xmin>1263</xmin>
      <ymax>494</ymax>
      <ymin>350</ymin>
    </bndbox>
    <difficult>0</difficult>
    <name>Gate Rupture</name>
    <pose>Unspecified</pose>
    <truncated>0</truncated>
  </object>
  <object>
    <bndbox>
      <xmax>488</xmax>
      <xmin>459</xmin>
      <ymax>491</ymax>
      <ymin>355</ymin>
    </bndbox>
    <difficult>0</difficult>
    <name>Gate Rupture</name>
    <pose>Unspecified</pose>
    <truncated>0</truncated>
  </object>
  <object>
    <bndbox>
      <xmax>418</xmax>
      <xmin>387</xmin>
      <ymax>785</ymax>
      <ymin>641</ymin>
    </bndbox>
    <difficult>0</difficult>
    <name>Gate Rupture</name>
    <pose>Unspecified</pose>
    <truncated>0</truncated>
  </object>
  <object>
    <bndbox>
      <xmax>1665</xmax>
      <xmin>1635</xmin>
      <ymax>495</ymax>
      <ymin>352</ymin>
    </bndbox>
    <difficult>0</difficult>
    <name>Gate Rupture</name>
    <pose>Unspecified</pose>
    <truncated>0</truncated>
  </object>
  <object>
    <bndbox>
      <xmax>207</xmax>
      <xmin>166</xmin>
      <ymax>206</ymax>
      <ymin>63</ymin>
    </bndbox>
    <difficult>0</difficult>
    <name>Gate Rupture</name>
    <pose>Unspecified</pose>
    <truncated>0</truncated>
  </object>
  <object>
    <bndbox>
      <xmax>204</xmax>
      <xmin>165</xmin>
      <ymax>784</ymax>
      <ymin>639</ymin>
    </bndbox>
    <difficult>0</difficult>
    <name>Gate Rupture</name>
    <pose>Unspecified</pose>
    <truncated>0</truncated>
  </object>
  <object>
    <bndbox>
      <xmax>343</xmax>
      <xmin>311</xmin>
      <ymax>784</ymax>
      <ymin>645</ymin>
    </bndbox>
    <difficult>0</difficult>
    <name>Gate Rupture</name>
    <pose>Unspecified</pose>
    <truncated>0</truncated>
  </object>
  <object>
    <bndbox>
      <xmax>271</xmax>
      <xmin>237</xmin>
      <ymax>786</ymax>
      <ymin>641</ymin>
    </bndbox>
    <difficult>0</difficult>
    <name>Gate Rupture</name>
    <pose>Unspecified</pose>
    <truncated>0</truncated>
  </object>
  <object>
    <bndbox>
      <xmax>1216</xmax>
      <xmin>1183</xmin>
      <ymax>205</ymax>
      <ymin>61</ymin>
    </bndbox>
    <difficult>0</difficult>
    <name>Gate Rupture</name>
    <pose>Unspecified</pose>
    <truncated>0</truncated>
  </object>
  <object>
    <bndbox>
      <xmax>1143</xmax>
      <xmin>1100</xmin>
      <ymax>205</ymax>
      <ymin>61</ymin>
    </bndbox>
    <difficult>0</difficult>
    <name>Gate Rupture</name>
    <pose>Unspecified</pose>
    <truncated>0</truncated>
  </object>
  <object>
    <bndbox>
      <xmax>1512</xmax>
      <xmin>1478</xmin>
      <ymax>203</ymax>
      <ymin>59</ymin>
    </bndbox>
    <difficult>0</difficult>
    <name>Gate Rupture</name>
    <pose>Unspecified</pose>
    <truncated>0</truncated>
  </object>
  <object>
    <bndbox>
      <xmax>1616</xmax>
      <xmin>1565</xmin>
      <ymax>752</ymax>
      <ymin>661</ymin>
    </bndbox>
    <difficult>0</difficult>
    <name>Black Spot</name>
    <pose>Unspecified</pose>
    <truncated>0</truncated>
  </object>
  <object>
    <bndbox>
      <xmax>1033</xmax>
      <xmin>998</xmin>
      <ymax>750</ymax>
      <ymin>697</ymin>
    </bndbox>
    <difficult>0</difficult>
    <name>Black Spot</name>
    <pose>Unspecified</pose>
    <truncated>0</truncated>
  </object>
  <object>
    <bndbox>
      <xmax>783</xmax>
      <xmin>749</xmin>
      <ymax>934</ymax>
      <ymin>788</ymin>
    </bndbox>
    <difficult>0</difficult>
    <name>Gate Rupture</name>
    <pose>Unspecified</pose>
    <truncated>0</truncated>
  </object>
  <object>
    <bndbox>
      <xmax>1615</xmax>
      <xmin>1572</xmin>
      <ymax>640</ymax>
      <ymin>497</ymin>
    </bndbox>
    <difficult>0</difficult>
    <name>Gate Rupture</name>
    <pose>Unspecified</pose>
    <truncated>0</truncated>
  </object>
  <object>
    <bndbox>
      <xmax>761</xmax>
      <xmin>730</xmin>
      <ymax>414</ymax>
      <ymin>384</ymin>
    </bndbox>
    <difficult>0</difficult>
    <name>Snowflake Spot</name>
    <pose>Unspecified</pose>
    <truncated>0</truncated>
  </object>
  <object>
    <bndbox>
      <xmax>1369</xmax>
      <xmin>1338</xmin>
      <ymax>725</ymax>
      <ymin>672</ymin>
    </bndbox>
    <difficult>0</difficult>
    <name>Black Spot</name>
    <pose>Unspecified</pose>
    <truncated>0</truncated>
  </object>
  <object>
    <bndbox>
      <xmax>1449</xmax>
      <xmin>1415</xmin>
      <ymax>892</ymax>
      <ymin>829</ymin>
    </bndbox>
    <difficult>0</difficult>
    <name>Black Spot</name>
    <pose>Unspecified</pose>
    <truncated>0</truncated>
  </object>
  <object>
    <bndbox>
      <xmax>1302</xmax>
      <xmin>1269</xmin>
      <ymax>789</ymax>
      <ymin>655</ymin>
    </bndbox>
    <difficult>0</difficult>
    <name>Black Spot</name>
    <pose>Unspecified</pose>
    <truncated>0</truncated>
  </object>
  <object>
    <bndbox>
      <xmax>305</xmax>
      <xmin>285</xmin>
      <ymax>761</ymax>
      <ymin>718</ymin>
    </bndbox>
    <difficult>0</difficult>
    <name>Black Spot</name>
    <pose>Unspecified</pose>
    <truncated>0</truncated>
  </object>
  <object>
    <bndbox>
      <xmax>705</xmax>
      <xmin>680</xmin>
      <ymax>898</ymax>
      <ymin>839</ymin>
    </bndbox>
    <difficult>0</difficult>
    <name>Black Spot</name>
    <pose>Unspecified</pose>
    <truncated>0</truncated>
  </object>
  <object>
    <bndbox>
      <xmax>639</xmax>
      <xmin>610</xmin>
      <ymax>497</ymax>
      <ymin>352</ymin>
    </bndbox>
    <difficult>0</difficult>
    <name>Gate Rupture</name>
    <pose>Unspecified</pose>
    <truncated>0</truncated>
  </object>
  <object>
    <bndbox>
      <xmax>700</xmax>
      <xmin>671</xmin>
      <ymax>352</ymax>
      <ymin>206</ymin>
    </bndbox>
    <difficult>0</difficult>
    <name>Gate Rupture</name>
    <pose>Unspecified</pose>
    <truncated>0</truncated>
  </object>
  <object>
    <bndbox>
      <xmax>775</xmax>
      <xmin>739</xmin>
      <ymax>351</ymax>
      <ymin>208</ymin>
    </bndbox>
    <difficult>0</difficult>
    <name>Gate Rupture</name>
    <pose>Unspecified</pose>
    <truncated>0</truncated>
  </object>
  <object>
    <bndbox>
      <xmax>252</xmax>
      <xmin>225</xmin>
      <ymax>351</ymax>
      <ymin>211</ymin>
    </bndbox>
    <difficult>0</difficult>
    <name>Gate Rupture</name>
    <pose>Unspecified</pose>
    <truncated>0</truncated>
  </object>
  <object>
    <bndbox>
      <xmax>418</xmax>
      <xmin>383</xmin>
      <ymax>208</ymax>
      <ymin>64</ymin>
    </bndbox>
    <difficult>0</difficult>
    <name>Gate Rupture</name>
    <pose>Unspecified</pose>
    <truncated>0</truncated>
  </object>
  <object>
    <bndbox>
      <xmax>271</xmax>
      <xmin>241</xmin>
      <ymax>205</ymax>
      <ymin>62</ymin>
    </bndbox>
    <difficult>0</difficult>
    <name>Gate Rupture</name>
    <pose>Unspecified</pose>
    <truncated>0</truncated>
  </object>
  <object>
    <bndbox>
      <xmax>1520</xmax>
      <xmin>1488</xmin>
      <ymax>935</ymax>
      <ymin>785</ymin>
    </bndbox>
    <difficult>0</difficult>
    <name>Gate Rupture</name>
    <pose>Unspecified</pose>
    <truncated>0</truncated>
  </object>
  <object>
    <bndbox>
      <xmax>1600</xmax>
      <xmin>1568</xmin>
      <ymax>348</ymax>
      <ymin>202</ymin>
    </bndbox>
    <difficult>0</difficult>
    <name>Gate Rupture</name>
    <pose>Unspecified</pose>
    <truncated>0</truncated>
  </object>
  <object>
    <bndbox>
      <xmax>631</xmax>
      <xmin>597</xmin>
      <ymax>730</ymax>
      <ymin>680</ymin>
    </bndbox>
    <difficult>0</difficult>
    <name>Black Spot</name>
    <pose>Unspecified</pose>
    <truncated>0</truncated>
  </object>
  <object>
    <bndbox>
      <xmax>1816</xmax>
      <xmin>1780</xmin>
      <ymax>857</ymax>
      <ymin>809</ymin>
    </bndbox>
    <difficult>0</difficult>
    <name>Black Spot</name>
    <pose>Unspecified</pose>
    <truncated>0</truncated>
  </object>
  <path>./../assets/NG/NG-249.jpg</path>
  <segmented>0</segmented>
  <size>
    <depth>3</depth>
    <height>981</height>
    <width>1837</width>
  </size>
  <source>
    <database>Unknown</database>
  </source>
</annotation>